<?xml version="1.0" encoding="UTF-8"?><record_update table="sys_ux_client_script">
    <sys_ux_client_script action="DELETE">
        <controller_preset/>
        <includes/>
        <macroponent display_value="Default">76d0cc61472df1105d6c8fd4f16d43e8</macroponent>
        <name>version_1/items</name>
        <preset/>
        <required_translations>[]</required_translations>
        <script><![CDATA[/**
 * @param {params} params
 * @param {api} params.api
 * @param {TransformApiHelpers} params.helpers
 */
function evaluateProperty({    api,    state,    helpers}) {
    console.log("EVALUATE PROPERTY for Version 1");
    const selectedVersion2 = api.state.version_2[0];
    console.log("selectedVersion2 = ", selectedVersion2);
    const filteredList = api.data.getkbversions.output.filter(version => version.id !== selectedVersion2);
    console.log("filteredList = ", filteredList);
    return filteredList;
}]]></script>
        <script_api_version>2.0.0</script_api_version>
        <sys_class_name>sys_ux_client_script</sys_class_name>
        <sys_created_by>Marc.Mouries</sys_created_by>
        <sys_created_on>2023-09-28 22:12:55</sys_created_on>
        <sys_id>903d36bd4769b1105d6c8fd4f16d431e</sys_id>
        <sys_mod_count>23</sys_mod_count>
        <sys_name>version_1/items</sys_name>
        <sys_package display_value="Creator Innovation Gallery" source="x_snc_uib_examples">a0a606201b0f8510ce2b6579b04bcb65</sys_package>
        <sys_policy/>
        <sys_scope display_value="Creator Innovation Gallery">a0a606201b0f8510ce2b6579b04bcb65</sys_scope>
        <sys_update_name>sys_ux_client_script_903d36bd4769b1105d6c8fd4f16d431e</sys_update_name>
        <sys_updated_by>Marc.Mouries</sys_updated_by>
        <sys_updated_on>2025-01-10 21:15:24</sys_updated_on>
        <target>macroponent</target>
        <type>transform</type>
    </sys_ux_client_script>
    <sys_update_version action="INSERT_OR_UPDATE">
        <action>DELETE</action>
        <application display_value="Creator Innovation Gallery">a0a606201b0f8510ce2b6579b04bcb65</application>
        <file_path/>
        <instance_id>bed3c2091b56b11ce84d2f8dee4bcbd7</instance_id>
        <instance_name>marco</instance_name>
        <name>sys_ux_client_script_903d36bd4769b1105d6c8fd4f16d431e</name>
        <payload>&lt;?xml version="1.0" encoding="UTF-8"?&gt;&lt;record_update table="sys_ux_client_script"&gt;&lt;sys_ux_client_script action="INSERT_OR_UPDATE"&gt;&lt;controller_preset/&gt;&lt;includes/&gt;&lt;macroponent display_value="Default"&gt;76d0cc61472df1105d6c8fd4f16d43e8&lt;/macroponent&gt;&lt;name&gt;version_1/items&lt;/name&gt;&lt;preset/&gt;&lt;required_translations&gt;[]&lt;/required_translations&gt;&lt;script&gt;&lt;![CDATA[/**
 * @param {params} params
 * @param {api} params.api
 * @param {TransformApiHelpers} params.helpers
 */
function evaluateProperty({    api,    state,    helpers}) {
    console.log("EVALUATE PROPERTY for Version 1");
    const selectedVersion2 = api.state.version_2[0];
    console.log("selectedVersion2 = ", selectedVersion2);
    const filteredList = api.data.getkbversions.output.filter(version =&gt; version.id !== selectedVersion2);
    console.log("filteredList = ", filteredList);
    return filteredList;
}]]&gt;&lt;/script&gt;&lt;script_api_version&gt;2.0.0&lt;/script_api_version&gt;&lt;sys_class_name&gt;sys_ux_client_script&lt;/sys_class_name&gt;&lt;sys_created_by&gt;Marc.Mouries&lt;/sys_created_by&gt;&lt;sys_created_on&gt;2023-09-28 22:12:55&lt;/sys_created_on&gt;&lt;sys_id&gt;903d36bd4769b1105d6c8fd4f16d431e&lt;/sys_id&gt;&lt;sys_mod_count&gt;23&lt;/sys_mod_count&gt;&lt;sys_name&gt;version_1/items&lt;/sys_name&gt;&lt;sys_package display_value="Creator Innovation Gallery" source="x_snc_uib_examples"&gt;a0a606201b0f8510ce2b6579b04bcb65&lt;/sys_package&gt;&lt;sys_policy/&gt;&lt;sys_scope display_value="Creator Innovation Gallery"&gt;a0a606201b0f8510ce2b6579b04bcb65&lt;/sys_scope&gt;&lt;sys_update_name&gt;sys_ux_client_script_903d36bd4769b1105d6c8fd4f16d431e&lt;/sys_update_name&gt;&lt;sys_updated_by&gt;Marc.Mouries&lt;/sys_updated_by&gt;&lt;sys_updated_on&gt;2025-01-10 21:15:24&lt;/sys_updated_on&gt;&lt;target&gt;macroponent&lt;/target&gt;&lt;type&gt;transform&lt;/type&gt;&lt;/sys_ux_client_script&gt;&lt;/record_update&gt;</payload>
        <payload_hash>1806704375</payload_hash>
        <record_name>version_1/items</record_name>
        <reverted_from/>
        <source>a840afd0fbc3d2107b04ff4655efdc83</source>
        <source_table>sys_update_set</source_table>
        <state>previous</state>
        <sys_created_by>Marc.Mouries</sys_created_by>
        <sys_created_on>2025-01-10 21:15:25</sys_created_on>
        <sys_id>80bc8701fbc712107b04ff4655efdcb2</sys_id>
        <sys_mod_count>0</sys_mod_count>
        <sys_recorded_at>1945212660a0000001</sys_recorded_at>
        <sys_updated_by>Marc.Mouries</sys_updated_by>
        <sys_updated_on>2025-01-10 21:15:25</sys_updated_on>
        <type>UX Client Script</type>
        <update_guid>08bc870104c7121057983db47903d8b1</update_guid>
        <update_guid_history>08bc870104c7121057983db47903d8b1:1806704375,8939ea05a6c312102cb2281599c7710e:1972833403,08a8a6c11ec3121027966068753bff60:-1510474221,133866c15ac312109ade444bda3774e6:2081987112,574c820109c39610cc9ce90fe531985f:-1201447368,4bacb9c677620650a3628f28bbb033f8:-1257657392</update_guid_history>
    </sys_update_version>
    <sys_metadata_delete action="INSERT_OR_UPDATE">
        <sys_audit_delete/>
        <sys_class_name>sys_metadata_delete</sys_class_name>
        <sys_created_by>Marc.Mouries</sys_created_by>
        <sys_created_on>2025-01-10 21:25:10</sys_created_on>
        <sys_db_object display_value="" name="sys_ux_client_script">sys_ux_client_script</sys_db_object>
        <sys_id>4a34291074594958bfdf137f11e4cd04</sys_id>
        <sys_metadata>903d36bd4769b1105d6c8fd4f16d431e</sys_metadata>
        <sys_mod_count>0</sys_mod_count>
        <sys_name>version_1/items</sys_name>
        <sys_package display_value="Creator Innovation Gallery" source="x_snc_uib_examples">a0a606201b0f8510ce2b6579b04bcb65</sys_package>
        <sys_parent/>
        <sys_policy/>
        <sys_scope display_value="Creator Innovation Gallery">a0a606201b0f8510ce2b6579b04bcb65</sys_scope>
        <sys_scope_delete display_value="">4e87e5c7db26498091c96a6b2a7a0e10</sys_scope_delete>
        <sys_update_name>sys_ux_client_script_903d36bd4769b1105d6c8fd4f16d431e</sys_update_name>
        <sys_update_version display_value="sys_ux_client_script_903d36bd4769b1105d6c8fd4f16d431e">80bc8701fbc712107b04ff4655efdcb2</sys_update_version>
        <sys_updated_by>Marc.Mouries</sys_updated_by>
        <sys_updated_on>2025-01-10 21:25:10</sys_updated_on>
    </sys_metadata_delete>
</record_update>
